[{"url": "https://garotanocontrole.com.br/2020/06/porque-pokemon-unite-e-importante/", "date": "25/6/2020", "title": "Porque Pok\u00e9mon Unite \u00e9 importante?"}, {"url": "https://garotanocontrole.com.br/2020/06/quem-e-jesse-jacobs/", "date": "20/6/2020", "title": "Quem \u00e9 Jesse Jacobs?"}, {"url": "https://garotanocontrole.com.br/2020/06/horizon-zero-dawn-pos-apocalipse-e-religiao/", "date": "15/6/2020", "title": "Horizon Zero Dawn: P\u00f3s apocalipse e Religi\u00e3o"}, {"url": "https://garotanocontrole.com.br/2020/06/zelda-e-o-budismo/", "date": "9/6/2020", "title": "Zelda e o Budismo"}, {"url": "https://garotanocontrole.com.br/2020/06/gamification-na-sua-vida/", "date": "1/6/2020", "title": "Gamification na sua vida"}, {"url": "https://garotanocontrole.com.br/2020/05/quem-e-a-vanillaware/", "date": "26/5/2020", "title": "Quem \u00e9 a Vanillaware?"}, {"url": "https://garotanocontrole.com.br/2020/05/the-hobbit-1982-uma-evolucao-no-adventure-text/", "date": "25/5/2020", "title": "The Hobbit  (1982) \u2013 Uma evolu\u00e7\u00e3o no Adventure-Text"}, {"url": "https://garotanocontrole.com.br/2020/05/persona-5-interface-em-jogos/", "date": "25/5/2020", "title": "Persona 5 \u2013 Interface em Jogos"}, {"url": "https://garotanocontrole.com.br/2020/04/shadow-of-colossus/", "date": "24/4/2020", "title": "Shadow of the Colossus \u2013 Interatividade e F\u00e9"}]